datasette_llm_accountant/__init__.py
datasette_llm_accountant/accountant.py
datasette_llm_accountant/hookspecs.py
datasette_llm_accountant/pricing.py
datasette_llm_accountant/wrapper.py
datasette_llm_accountant-0.1a0.dist-info/licenses/LICENSE
datasette_llm_accountant-0.1a0.dist-info/METADATA
datasette_llm_accountant-0.1a0.dist-info/WHEEL
datasette_llm_accountant-0.1a0.dist-info/entry_points.txt
datasette_llm_accountant-0.1a0.dist-info/top_level.txt
datasette_llm_accountant-0.1a0.dist-info/RECORD
