Metadata-Version: 2.4
Name: datasette-llm-accountant
Version: 0.1a0
Summary: Accounting for LLM token usage
Author: Simon Willison
License-Expression: Apache-2.0
Project-URL: Homepage, https://github.com/datasette/datasette-llm-accountant
Project-URL: Changelog, https://github.com/datasette/datasette-llm-accountant/releases
Project-URL: Issues, https://github.com/datasette/datasette-llm-accountant/issues
Project-URL: CI, https://github.com/datasette/datasette-llm-accountant/actions
Classifier: Framework :: Datasette
Requires-Python: >=3.10
License-File: LICENSE
Requires-Dist: datasette>=1.0a21
Requires-Dist: llm
Requires-Dist: httpx
Provides-Extra: test
Requires-Dist: pytest; extra == "test"
Requires-Dist: pytest-asyncio; extra == "test"
Requires-Dist: sqlite-utils; extra == "test"
Dynamic: license-file
